./.gitignore
./LICENSE
./PKG-INFO
./README.md
./app.py
./language.json
./package_name
./push_info.json
./pyproject.toml
./requirements.txt
./server_config.json
iflow_mcp_danielpeter_99_calcom_mcp-0.1.1.dist-info/METADATA
iflow_mcp_danielpeter_99_calcom_mcp-0.1.1.dist-info/WHEEL
iflow_mcp_danielpeter_99_calcom_mcp-0.1.1.dist-info/entry_points.txt
iflow_mcp_danielpeter_99_calcom_mcp-0.1.1.dist-info/licenses/LICENSE
iflow_mcp_danielpeter_99_calcom_mcp-0.1.1.dist-info/RECORD
