Metadata-Version: 2.4
Name: iflow-mcp-danielpeter-99-calcom-mcp
Version: 0.1.1
Summary: A FastMCP server for interacting with the Cal.com API
License-File: LICENSE
Requires-Python: >=3.8
Requires-Dist: fastmcp>=0.1.0
Requires-Dist: python-dotenv>=1.0.0
Requires-Dist: requests>=2.31.0
